dynafile/__init__.py
dynafile/dispatcher.py
dynafile-0.1.3.dist-info/METADATA
dynafile-0.1.3.dist-info/WHEEL
dynafile-0.1.3.dist-info/licenses/LICENSE
dynafile-0.1.3.dist-info/RECORD
