Metadata-Version: 2.3
Name: dynafile
Version: 0.1.3
Summary: NoSQLDB following the Dynamo concept, but for a filebased embedded db.
Author-email: Maic Siemering <maic@siemering.tech>
License-Expression: MIT
License-File: LICENSE
Keywords: database,nosql
Classifier: Development Status :: 3 - Alpha
Classifier: Intended Audience :: Developers
Classifier: Intended Audience :: System Administrators
Classifier: License :: OSI Approved :: MIT License
Classifier: Operating System :: OS Independent
Classifier: Programming Language :: Python :: 3
Classifier: Programming Language :: Python :: 3.8
Classifier: Programming Language :: Python :: 3.9
Classifier: Programming Language :: Python :: 3.10
Classifier: Programming Language :: Python :: 3.11
Classifier: Programming Language :: Python :: 3.12
Classifier: Programming Language :: Python :: Implementation :: CPython
Classifier: Programming Language :: Python :: Implementation :: PyPy
Classifier: Topic :: Database
Classifier: Topic :: Utilities
Classifier: Typing :: Typed
Requires-Python: >=3.8
Requires-Dist: atomicwrites>=1.4.1
Requires-Dist: sortedcontainers>=2.4.0
Provides-Extra: filter
Requires-Dist: filtration>=2.3.0; extra == 'filter'
